[
    {
        "rank": "1",
        "name": "james_polhill",
        "score": "369"
    },
    {
        "rank": "2",
        "name": "streetervilled1",
        "score": "368"
    },
    {
        "rank": "3",
        "name": "geist254",
        "score": "364"
    },
    {
        "rank": "4",
        "name": "santandood",
        "score": "359"
    },
    {
        "rank": "5",
        "name": "0nelinewonder",
        "score": "358"
    },
    {
        "rank": "6",
        "name": "opulentdecision",
        "score": "357"
    },
    {
        "rank": "7",
        "name": "jivedoodle",
        "score": "353"
    },
    {
        "rank": "8",
        "name": "oliver13h",
        "score": "351"
    },
    {
        "rank": "9",
        "name": "tasty_snackz",
        "score": "342"
    },
    {
        "rank": "10",
        "name": "moonshotkongz",
        "score": "333"
    },
    {
        "rank": "11",
        "name": "the_waco_kid1",
        "score": "323"
    },
    {
        "rank": "12",
        "name": "kayshhhmo",
        "score": "315"
    },
    {
        "rank": "13",
        "name": "soybienmamon",
        "score": "311"
    },
    {
        "rank": "14",
        "name": "montiweb3",
        "score": "309"
    },
    {
        "rank": "15",
        "name": "bitrise25",
        "score": "306"
    },
    {
        "rank": "16",
        "name": "mace1337ftw",
        "score": "305"
    },
    {
        "rank": "17",
        "name": "0xbjartek",
        "score": "303"
    },
    {
        "rank": "18",
        "name": "ryrotaco",
        "score": "302"
    },
    {
        "rank": "19",
        "name": "doodcollects",
        "score": "297"
    },
    {
        "rank": "20",
        "name": "cociboni",
        "score": "296"
    },
    {
        "rank": "21",
        "name": "skeens_jeremy",
        "score": "296"
    },
    {
        "rank": "22",
        "name": "km404atl",
        "score": "294"
    },
    {
        "rank": "23",
        "name": "doubtmeharder",
        "score": "291"
    },
    {
        "rank": "24",
        "name": "brucelane0",
        "score": "291"
    },
    {
        "rank": "25",
        "name": "pufferupdoodle",
        "score": "283"
    },
    {
        "rank": "26",
        "name": "make_ithappenn",
        "score": "281"
    },
    {
        "rank": "27",
        "name": "nrd_design",
        "score": "279"
    },
    {
        "rank": "28",
        "name": "petranto12",
        "score": "264"
    },
    {
        "rank": "29",
        "name": "outsidethe0x",
        "score": "251"
    },
    {
        "rank": "30",
        "name": "thenftshack",
        "score": "204"
    },
    {
        "rank": "31",
        "name": "vonfrontin",
        "score": "204"
    },
    {
        "rank": "32",
        "name": "skr_ventures",
        "score": "200"
    },
    {
        "rank": "33",
        "name": "tonoboon",
        "score": "189"
    },
    {
        "rank": "34",
        "name": "digikelly",
        "score": "186"
    },
    {
        "rank": "35",
        "name": "ericdzengeleski",
        "score": "181"
    },
    {
        "rank": "36",
        "name": "mrcookiesnft",
        "score": "172"
    },
    {
        "rank": "37",
        "name": "bigdaddyerac",
        "score": "168"
    },
    {
        "rank": "38",
        "name": "happy_dood_",
        "score": "154"
    },
    {
        "rank": "39",
        "name": "tappi365",
        "score": "150"
    },
    {
        "rank": "40",
        "name": "hazy_purps",
        "score": "146"
    },
    {
        "rank": "41",
        "name": "dingo522left",
        "score": "135"
    },
    {
        "rank": "42",
        "name": "jfitz_21",
        "score": "134"
    },
    {
        "rank": "43",
        "name": "ohtobisan",
        "score": "131"
    },
    {
        "rank": "44",
        "name": "in2nfts",
        "score": "131"
    },
    {
        "rank": "45",
        "name": "concrete_barber",
        "score": "125"
    },
    {
        "rank": "46",
        "name": "squ1nch",
        "score": "93"
    },
    {
        "rank": "47",
        "name": "supermoooooo1",
        "score": "91"
    },
    {
        "rank": "48",
        "name": "conquant",
        "score": "77"
    },
    {
        "rank": "49",
        "name": "troyapeman",
        "score": "65"
    },
    {
        "rank": "50",
        "name": "aleon523",
        "score": "64"
    },
    {
        "rank": "51",
        "name": "yankun811203",
        "score": "54"
    },
    {
        "rank": "52",
        "name": "tungweb3",
        "score": "43"
    },
    {
        "rank": "53",
        "name": "yuehfengmon",
        "score": "39"
    },
    {
        "rank": "54",
        "name": "mr_meridian",
        "score": "28"
    },
    {
        "rank": "55",
        "name": "goofball851",
        "score": "25"
    },
    {
        "rank": "56",
        "name": "pukemrs",
        "score": "22"
    },
    {
        "rank": "57",
        "name": "chouyenchun1",
        "score": "20"
    },
    {
        "rank": "58",
        "name": "wax_weazle",
        "score": "17"
    },
    {
        "rank": "59",
        "name": "0xjunkim",
        "score": "17"
    },
    {
        "rank": "60",
        "name": "spacecowboy2300",
        "score": "14"
    },
    {
        "rank": "61",
        "name": "auscryptoboy",
        "score": "12"
    },
    {
        "rank": "62",
        "name": "dreamcar_coin",
        "score": "10"
    },
    {
        "rank": "63",
        "name": "beecass_93",
        "score": "7"
    },
    {
        "rank": "64",
        "name": "0xfbm",
        "score": "4"
    },
    {
        "rank": "65",
        "name": "ginsu_eth",
        "score": "1"
    },
    {
        "rank": "66",
        "name": "lordoftheidiot5",
        "score": "0"
    },
    {
        "rank": "67",
        "name": "atownbrown",
        "score": "0"
    },
    {
        "rank": "68",
        "name": "nfungiblemotion",
        "score": "0"
    },
    {
        "rank": "69",
        "name": "vmaldonadoc204",
        "score": "0"
    },
    {
        "rank": "70",
        "name": "wotwibot",
        "score": "0"
    },
    {
        "rank": "71",
        "name": "ManuismeNguyen",
        "score": "0"
    },
    {
        "rank": "72",
        "name": "wingnnit",
        "score": "0"
    },
    {
        "rank": "73",
        "name": "oklepatzky",
        "score": "0"
    },
    {
        "rank": "74",
        "name": "ryanhendler1",
        "score": "0"
    },
    {
        "rank": "75",
        "name": "datho09",
        "score": "0"
    },
    {
        "rank": "76",
        "name": "sushentalwar",
        "score": "0"
    },
    {
        "rank": "77",
        "name": "small__arms",
        "score": "0"
    },
    {
        "rank": "78",
        "name": "mriteeth",
        "score": "0"
    },
    {
        "rank": "79",
        "name": "majimeqqq",
        "score": "0"
    },
    {
        "rank": "80",
        "name": "@OlabanjiOlalek2",
        "score": "0"
    },
    {
        "rank": "81",
        "name": "Intyxfgt",
        "score": "0"
    },
    {
        "rank": "82",
        "name": "7dubs",
        "score": "0"
    },
    {
        "rank": "83",
        "name": "farindet29clone",
        "score": "0"
    },
    {
        "rank": "84",
        "name": "credzilla",
        "score": "0"
    },
    {
        "rank": "85",
        "name": "shuttergod",
        "score": "0"
    },
    {
        "rank": "86",
        "name": "maomin_9526",
        "score": "0"
    },
    {
        "rank": "87",
        "name": "riotact_",
        "score": "0"
    },
    {
        "rank": "88",
        "name": "g01dy49",
        "score": "0"
    },
    {
        "rank": "89",
        "name": "bitorcom",
        "score": "0"
    },
    {
        "rank": "90",
        "name": "niftydudes",
        "score": "0"
    },
    {
        "rank": "91",
        "name": "dbrightnat",
        "score": "0"
    },
    {
        "rank": "92",
        "name": "canito_eth",
        "score": "0"
    },
    {
        "rank": "93",
        "name": "favoriteloner",
        "score": "0"
    },
    {
        "rank": "94",
        "name": "densesyntax",
        "score": "0"
    }
]